{
  "metadata": {
    "name": "Board Game Components Library",
    "version": "0.9.0",
    "created_at": "2024-01-15T10:00:00Z",
    "description": "Sample game components library for dhash migration testing",
    "migration": {
      "migrated_at": "2025-09-24T16:12:33.846Z",
      "source_file": "library.json",
      "migration_version": "1.0.0",
      "total_components": 7,
      "low_confidence_count": 0,
      "average_confidence": 0.9571428571428572
    }
  },
  "components": [
    {
      "name": "Wooden Meeples",
      "quantity": 50,
      "description": "Small wooden game pieces in various colors for player representation",
      "image": "/images/meeples.jpg",
      "category": "pieces",
      "material": "wood",
      "dhash": "1268a3673dc95210",
      "migrated_at": "2025-09-24T16:12:33.846Z",
      "migration_confidence": 1
    },
    {
      "name": "Action Cards",
      "quantity": 120,
      "description": "Premium cardstock action cards with special abilities",
      "image": "/images/action_cards.jpg",
      "category": "cards",
      "material": "cardstock",
      "dhash": "03f2743253b2f0c4",
      "migrated_at": "2025-09-24T16:12:33.846Z",
      "migration_confidence": 1
    },
    {
      "name": "Game Board",
      "quantity": 1,
      "description": "Main game board with hexagonal grid layout",
      "image": "/images/game_board.jpg",
      "category": "board",
      "material": "cardboard",
      "dhash": "218ba4a820e7cdbe",
      "migrated_at": "2025-09-24T16:12:33.846Z",
      "migration_confidence": 1,
      "legacy_image_metadata": {
        "size": "large",
        "resolution": "300dpi",
        "color_profile": "sRGB"
      }
    },
    {
      "name": "Dice Set",
      "quantity": 6,
      "description": "Six-sided dice in player colors",
      "image": "/images/dice_set.jpg",
      "category": "dice",
      "material": "plastic",
      "dhash": "a397e6f912df1b84",
      "migrated_at": "2025-09-24T16:12:33.846Z",
      "migration_confidence": 1
    },
    {
      "name": "Resource Tokens",
      "quantity": 75,
      "description": "Cardboard tokens representing different resources",
      "image": "/images/resource_tokens.jpg",
      "category": "tokens",
      "material": "cardboard",
      "dhash": "56a05617190f221b",
      "migrated_at": "2025-09-24T16:12:33.846Z",
      "migration_confidence": 1
    },
    {
      "name": "Player Mats",
      "quantity": 4,
      "description": "Individual player boards for tracking progress",
      "category": "boards",
      "material": "cardboard",
      "dhash": "af18a92a39d4c8f7",
      "migrated_at": "2025-09-24T16:12:33.846Z",
      "migration_confidence": 0.7
    },
    {
      "name": "Reference Cards",
      "quantity": 8,
      "description": "Quick reference cards for game rules",
      "image": "/images/reference_cards.jpg",
      "category": "cards",
      "material": "cardstock",
      "dhash": "1fb128a2ff4835b2",
      "migrated_at": "2025-09-24T16:12:33.846Z",
      "migration_confidence": 1
    }
  ]
}